{"about_constitution.md":"DOAG5OL8","about_faq.md":"D7cv0UqQ","about_history.md":"Efiia3vT","about_honor.md":"COJcidzm","about_introduction.md":"DOrrAhat","about_join-us.md":"dm-F9GCy","about_support.md":"Kyjyuo-2","about_wechat.md":"DSqeItO_","basic_basic.md":"DtF2aW_K","basic_binary.md":"CFyp0rYx","basic_complexity.md":"_gL8Ub7s","basic_divide.md":"Bj5UhirS","basic_dp.md":"BCT4h6cG","basic_grammer_enviroment.md":"CeCReDS1","basic_grammer_intro.md":"WA9vdvWA","basic_grammer_markdown.md":"CBO2GbhK","basic_greedy.md":"_Cj8cSu-","basic_how-to-train.md":"DaGQuxeu","basic_index.md":"Btsss_iV","basic_intro.md":"CHZ-Zuxr","basic_prefix-sum.md":"gbpBlINy","basic_quick-pow.md":"DhBg50_N","basic_recursion.md":"By82duvV","basic_sort.md":"fFX9Exhe","index.md":"Cgm_VouA","math_crt.md":"Cl04wNgW","math_dirichlet.md":"CuSvW9S8","math_game-theory.md":"CWH5qYJq","math_index.md":"D9KlexFC","math_multiplicative-function_index.md":"CK1HMSaS","math_multiplicative-function_min25.md":"DsLTqNoU","math_multiplicative-function_pn.md":"DgXabgK3","math_multiplicative-function_zhouge.md":"CN7YmDj_","math_poly_convolution.md":"Ba5U_G9m","math_poly_fft.md":"CII8i_lW","math_poly_index.md":"CTkYtINQ","math_poly_newton.md":"BJfJP-Tl","math_sieve.md":"DYeIm34X","other_english.md":"CKREuDLg","other_index.md":"piYBofZG","other_mkdocs.md":"Ck-ryxrd","string_index.md":"BWDlgLnj","string_minimal-string.md":"24P383R3","struct_fenwick-tree.md":"DMJ6uZpA","struct_index.md":"BnZMHbQz","struct_sparse-table.md":"CEVFHOgF"}
